dextrade/__init__.py
dextrade/api.py
dextrade/models.py
dextrade/websocket.py
dex_trade_api-0.1.0.dist-info/METADATA
dex_trade_api-0.1.0.dist-info/WHEEL
dex_trade_api-0.1.0.dist-info/RECORD
