Metadata-Version: 2.1
Name: dex-trade-api
Version: 0.1.0
Summary: Python client for the Dex-Trade cryptocurrency exchange API
Home-page: https://github.com/endogen/dex-trade-api
License: MIT
Keywords: cryptocurrency,exchange,trading,api,dex-trade
Author: endogen
Author-email: endogen@xian.org
Requires-Python: >=3.11,<4.0
Classifier: Development Status :: 4 - Beta
Classifier: Intended Audience :: Developers
Classifier: License :: OSI Approved :: MIT License
Classifier: Operating System :: OS Independent
Classifier: Programming Language :: Python :: 3
Classifier: Programming Language :: Python :: 3.11
Classifier: Programming Language :: Python :: 3.12
Classifier: Programming Language :: Python :: 3.13
Classifier: Topic :: Office/Business :: Financial :: Investment
Classifier: Topic :: Software Development :: Libraries :: Python Modules
Requires-Dist: python-dotenv (>=1.0.1,<2.0.0)
Requires-Dist: requests (>=2.32.3,<3.0.0)
Requires-Dist: websocket-client (>=1.7.0,<2.0.0)
Project-URL: Repository, https://github.com/endogen/dex-trade-api
